<?xml version="1.0" encoding="utf-8" ?>
<c2layout>
    <name>Vendas-EntregaItens</name>
    <sid>546384127207857</sid>
    <event-sheet>Vendas-EntregaItens</event-sheet>
    <size>
        <width>1308</width>
        <height>500</height>
    </size>
    <margins>
        <horizontal>500</horizontal>
        <vertical>500</vertical>
    </margins>
    <unbounded-scrolling>0</unbounded-scrolling>
    <layers>
        <layer name="Layer 0" sid="689374197915990">
            <initially-visible>1</initially-visible>
            <background-color>255,255,255</background-color>
            <transparent>0</transparent>
            <parallax>
                <x>1</x>
                <y>1</y>
            </parallax>
            <zoom-rate>1</zoom-rate>
            <opacity>1</opacity>
            <force-own-texture>0</force-own-texture>
            <global>0</global>
            <use-render-cells>0</use-render-cells>
            <blend-mode>0</blend-mode>
            <effect-fallback>0</effect-fallback>
            <instances>
                <instance type="paredeeee" uid="90">
                    <properties>
                        <initial-visibility>Visible</initial-visibility>
                        <initial-animation>Default</initial-animation>
                        <initial-frame>0</initial-frame>
                        <collisions>Enabled</collisions>
                    </properties>
                    <blend-mode>0</blend-mode>
                    <effect-fallback>0</effect-fallback>
                    <world>
                        <x>659</x>
                        <y>218</y>
                        <z>0</z>
                        <width>1354</width>
                        <height>428</height>
                        <depth>0</depth>
                        <hotspotX>0.5</hotspotX>
                        <hotspotY>0.5</hotspotY>
                        <angle>0</angle>
                        <opacity>1</opacity>
                    </world>
                </instance>
                <instance type="fundooooo" uid="131">
                    <properties>
                        <initial-visibility>Visible</initial-visibility>
                        <hotspot>Top-left</hotspot>
                    </properties>
                    <blend-mode>0</blend-mode>
                    <effect-fallback>0</effect-fallback>
                    <world>
                        <x>-18</x>
                        <y>-16</y>
                        <z>0</z>
                        <width>1357</width>
                        <height>512</height>
                        <depth>0</depth>
                        <hotspotX>0</hotspotX>
                        <hotspotY>0</hotspotY>
                        <angle>0</angle>
                        <opacity>1</opacity>
                    </world>
                </instance>
                <instance type="rodspe" uid="164">
                    <properties>
                        <initial-visibility>Visible</initial-visibility>
                        <initial-animation>Default</initial-animation>
                        <initial-frame>0</initial-frame>
                        <collisions>Enabled</collisions>
                    </properties>
                    <blend-mode>0</blend-mode>
                    <effect-fallback>0</effect-fallback>
                    <world>
                        <x>659</x>
                        <y>429</y>
                        <z>0</z>
                        <width>1353</width>
                        <height>38</height>
                        <depth>0</depth>
                        <hotspotX>0.5</hotspotX>
                        <hotspotY>0.5</hotspotY>
                        <angle>0</angle>
                        <opacity>1</opacity>
                    </world>
                </instance>
                <instance type="vhao" uid="246">
                    <properties>
                        <initial-visibility>Visible</initial-visibility>
                        <initial-animation>Default</initial-animation>
                        <initial-frame>0</initial-frame>
                        <collisions>Enabled</collisions>
                    </properties>
                    <blend-mode>0</blend-mode>
                    <effect-fallback>0</effect-fallback>
                    <world>
                        <x>585</x>
                        <y>250</y>
                        <z>0</z>
                        <width>1354</width>
                        <height>105</height>
                        <depth>0</depth>
                        <hotspotX>0.443895549</hotspotX>
                        <hotspotY>-1.881355882</hotspotY>
                        <angle>0</angle>
                        <opacity>1</opacity>
                    </world>
                </instance>
                <instance type="prat1" uid="260">
                    <properties>
                        <initial-visibility>Visible</initial-visibility>
                        <initial-animation>Default</initial-animation>
                        <initial-frame>0</initial-frame>
                        <collisions>Enabled</collisions>
                    </properties>
                    <blend-mode>0</blend-mode>
                    <effect-fallback>0</effect-fallback>
                    <world>
                        <x>502.192687988</x>
                        <y>329.42364502</y>
                        <z>0</z>
                        <width>232.276489258</width>
                        <height>267.191192627</height>
                        <depth>0</depth>
                        <hotspotX>0.5</hotspotX>
                        <hotspotY>0.507936537</hotspotY>
                        <angle>0</angle>
                        <opacity>1</opacity>
                    </world>
                </instance>
                <instance type="prat2" uid="261">
                    <properties>
                        <initial-visibility>Visible</initial-visibility>
                        <initial-animation>Default</initial-animation>
                        <initial-frame>0</initial-frame>
                        <collisions>Enabled</collisions>
                    </properties>
                    <blend-mode>0</blend-mode>
                    <effect-fallback>0</effect-fallback>
                    <world>
                        <x>821.081359863</x>
                        <y>381.454162598</y>
                        <z>0</z>
                        <width>291.784240723</width>
                        <height>160.574447632</height>
                        <depth>0</depth>
                        <hotspotX>0.5</hotspotX>
                        <hotspotY>0.507936537</hotspotY>
                        <angle>0</angle>
                        <opacity>1</opacity>
                    </world>
                </instance>
                <instance type="prat3" uid="262">
                    <properties>
                        <initial-visibility>Visible</initial-visibility>
                        <initial-animation>Default</initial-animation>
                        <initial-frame>0</initial-frame>
                        <collisions>Enabled</collisions>
                    </properties>
                    <blend-mode>0</blend-mode>
                    <effect-fallback>0</effect-fallback>
                    <world>
                        <x>1196.645507813</x>
                        <y>348.043701172</y>
                        <z>0</z>
                        <width>286.39654541</width>
                        <height>292.593994141</height>
                        <depth>0</depth>
                        <hotspotX>0.546875</hotspotX>
                        <hotspotY>0.587301612</hotspotY>
                        <angle>0</angle>
                        <opacity>1</opacity>
                    </world>
                </instance>
                <instance type="1d3" uid="900">
                    <properties>
                        <initial-visibility>Visible</initial-visibility>
                        <initial-animation>Default</initial-animation>
                        <initial-frame>0</initial-frame>
                        <collisions>Enabled</collisions>
                    </properties>
                    <blend-mode>0</blend-mode>
                    <effect-fallback>0</effect-fallback>
                    <world>
                        <x>1193</x>
                        <y>141</y>
                        <z>0</z>
                        <width>106</width>
                        <height>65</height>
                        <depth>0</depth>
                        <hotspotX>0.5</hotspotX>
                        <hotspotY>0.50222224</hotspotY>
                        <angle>0</angle>
                        <opacity>1</opacity>
                    </world>
                </instance>
                <instance type="qd2" uid="904">
                    <properties>
                        <initial-visibility>Visible</initial-visibility>
                        <initial-animation>Default</initial-animation>
                        <initial-frame>0</initial-frame>
                        <collisions>Enabled</collisions>
                    </properties>
                    <blend-mode>0</blend-mode>
                    <effect-fallback>0</effect-fallback>
                    <world>
                        <x>827</x>
                        <y>214</y>
                        <z>0</z>
                        <width>183</width>
                        <height>136</height>
                        <depth>0</depth>
                        <hotspotX>0.5</hotspotX>
                        <hotspotY>0.502262473</hotspotY>
                        <angle>0</angle>
                        <opacity>1</opacity>
                    </world>
                </instance>
                <instance type="qd1" uid="905">
                    <properties>
                        <initial-visibility>Visible</initial-visibility>
                        <initial-animation>Default</initial-animation>
                        <initial-frame>0</initial-frame>
                        <collisions>Enabled</collisions>
                    </properties>
                    <blend-mode>0</blend-mode>
                    <effect-fallback>0</effect-fallback>
                    <world>
                        <x>502</x>
                        <y>148</y>
                        <z>0</z>
                        <width>115</width>
                        <height>83</height>
                        <depth>0</depth>
                        <hotspotX>0.5</hotspotX>
                        <hotspotY>0.502325594</hotspotY>
                        <angle>0</angle>
                        <opacity>1</opacity>
                    </world>
                </instance>
                <instance type="herovei" uid="908">
                    <properties>
                        <initial-visibility>Invisible</initial-visibility>
                        <initial-animation>Default</initial-animation>
                        <initial-frame>0</initial-frame>
                        <collisions>Enabled</collisions>
                    </properties>
                    <behavior-instances>
                        <behavior-instance type="ScrollTo">
                            <properties>
                                <initial-state>Enabled</initial-state>
                            </properties>
                        </behavior-instance>
                        <behavior-instance type="Platform">
                            <properties>
                                <max-speed>330</max-speed>
                                <acceleration>1500</acceleration>
                                <deceleration>1500</deceleration>
                                <jump-strength>650</jump-strength>
                                <gravity>1500</gravity>
                                <max-fall-speed>1000</max-fall-speed>
                                <double-jump>Disabled</double-jump>
                                <jump-sustain>0</jump-sustain>
                                <default-controls>Yes</default-controls>
                                <initial-state>Enabled</initial-state>
                            </properties>
                        </behavior-instance>
                        <behavior-instance type="Pin" />
                    </behavior-instances>
                    <blend-mode>0</blend-mode>
                    <effect-fallback>0</effect-fallback>
                    <world>
                        <x>418</x>
                        <y>421</y>
                        <z>0</z>
                        <width>73</width>
                        <height>96</height>
                        <depth>0</depth>
                        <hotspotX>0.5</hotspotX>
                        <hotspotY>0.5</hotspotY>
                        <angle>0</angle>
                        <opacity>1</opacity>
                    </world>
                </instance>
                <instance type="VendasCli3" uid="909">
                    <properties>
                        <initial-visibility>Invisible</initial-visibility>
                        <initial-animation>Default</initial-animation>
                        <initial-frame>0</initial-frame>
                        <collisions>Enabled</collisions>
                    </properties>
                    <blend-mode>0</blend-mode>
                    <effect-fallback>0</effect-fallback>
                    <world>
                        <x>99</x>
                        <y>371</y>
                        <z>0</z>
                        <width>225</width>
                        <height>254</height>
                        <depth>0</depth>
                        <hotspotX>0.509433985</hotspotX>
                        <hotspotY>0.506493509</hotspotY>
                        <angle>0</angle>
                        <opacity>1</opacity>
                    </world>
                </instance>
                <instance type="VendasCli1" uid="910">
                    <properties>
                        <initial-visibility>Invisible</initial-visibility>
                        <initial-animation>Default</initial-animation>
                        <initial-frame>0</initial-frame>
                        <collisions>Enabled</collisions>
                    </properties>
                    <blend-mode>0</blend-mode>
                    <effect-fallback>0</effect-fallback>
                    <world>
                        <x>105</x>
                        <y>365</y>
                        <z>0</z>
                        <width>225</width>
                        <height>254</height>
                        <depth>0</depth>
                        <hotspotX>0.509433985</hotspotX>
                        <hotspotY>0.506493509</hotspotY>
                        <angle>0</angle>
                        <opacity>1</opacity>
                    </world>
                </instance>
                <instance type="VendasCli2" uid="911">
                    <properties>
                        <initial-visibility>Invisible</initial-visibility>
                        <initial-animation>Default</initial-animation>
                        <initial-frame>0</initial-frame>
                        <collisions>Enabled</collisions>
                    </properties>
                    <blend-mode>0</blend-mode>
                    <effect-fallback>0</effect-fallback>
                    <world>
                        <x>105</x>
                        <y>369</y>
                        <z>0</z>
                        <width>225</width>
                        <height>254</height>
                        <depth>0</depth>
                        <hotspotX>0.5</hotspotX>
                        <hotspotY>0.5</hotspotY>
                        <angle>0</angle>
                        <opacity>1</opacity>
                    </world>
                </instance>
                <instance type="baloonpedido" uid="912">
                    <properties>
                        <initial-visibility>Invisible</initial-visibility>
                        <initial-animation>Default</initial-animation>
                        <initial-frame>0</initial-frame>
                        <collisions>Enabled</collisions>
                    </properties>
                    <blend-mode>0</blend-mode>
                    <effect-fallback>0</effect-fallback>
                    <world>
                        <x>230.589706421</x>
                        <y>176.458496094</y>
                        <z>0</z>
                        <width>134</width>
                        <height>128</height>
                        <depth>0</depth>
                        <hotspotX>0.5</hotspotX>
                        <hotspotY>0.5</hotspotY>
                        <angle>0</angle>
                        <opacity>1</opacity>
                    </world>
                </instance>
                <instance type="imgLivroVendas" uid="913">
                    <properties>
                        <initial-visibility>Visible</initial-visibility>
                        <initial-animation>Default</initial-animation>
                        <initial-frame>0</initial-frame>
                        <collisions>Enabled</collisions>
                    </properties>
                    <behavior-instances>
                        <behavior-instance type="Pin" />
                    </behavior-instances>
                    <blend-mode>0</blend-mode>
                    <effect-fallback>0</effect-fallback>
                    <world>
                        <x>231.401672363</x>
                        <y>157.277450562</y>
                        <z>0</z>
                        <width>69</width>
                        <height>62</height>
                        <depth>0</depth>
                        <hotspotX>0.5</hotspotX>
                        <hotspotY>0.5</hotspotY>
                        <angle>0</angle>
                        <opacity>1</opacity>
                    </world>
                </instance>
                <instance type="cahu" uid="915">
                    <properties>
                        <initial-visibility>Invisible</initial-visibility>
                        <initial-animation>Default</initial-animation>
                        <initial-frame>0</initial-frame>
                        <collisions>Enabled</collisions>
                    </properties>
                    <behavior-instances>
                        <behavior-instance type="Solid">
                            <properties>
                                <initial-state>Enabled</initial-state>
                            </properties>
                        </behavior-instance>
                    </behavior-instances>
                    <blend-mode>0</blend-mode>
                    <effect-fallback>0</effect-fallback>
                    <world>
                        <x>643</x>
                        <y>487</y>
                        <z>0</z>
                        <width>1352</width>
                        <height>35</height>
                        <depth>0</depth>
                        <hotspotX>0.5</hotspotX>
                        <hotspotY>0.5</hotspotY>
                        <angle>0</angle>
                        <opacity>1</opacity>
                    </world>
                </instance>
                <instance type="paredaolimite" uid="916">
                    <properties>
                        <initial-visibility>Invisible</initial-visibility>
                        <initial-animation>Default</initial-animation>
                        <initial-frame>0</initial-frame>
                        <collisions>Enabled</collisions>
                    </properties>
                    <behavior-instances>
                        <behavior-instance type="Solid">
                            <properties>
                                <initial-state>Enabled</initial-state>
                            </properties>
                        </behavior-instance>
                    </behavior-instances>
                    <blend-mode>0</blend-mode>
                    <effect-fallback>0</effect-fallback>
                    <world>
                        <x>267</x>
                        <y>258</y>
                        <z>0</z>
                        <width>123</width>
                        <height>491</height>
                        <depth>0</depth>
                        <hotspotX>0.5</hotspotX>
                        <hotspotY>0.5</hotspotY>
                        <angle>0</angle>
                        <opacity>1</opacity>
                    </world>
                </instance>
                <instance type="paredaolimite" uid="917">
                    <properties>
                        <initial-visibility>Invisible</initial-visibility>
                        <initial-animation>Default</initial-animation>
                        <initial-frame>0</initial-frame>
                        <collisions>Enabled</collisions>
                    </properties>
                    <behavior-instances>
                        <behavior-instance type="Solid">
                            <properties>
                                <initial-state>Enabled</initial-state>
                            </properties>
                        </behavior-instance>
                    </behavior-instances>
                    <blend-mode>0</blend-mode>
                    <effect-fallback>0</effect-fallback>
                    <world>
                        <x>1375</x>
                        <y>271</y>
                        <z>0</z>
                        <width>123</width>
                        <height>491</height>
                        <depth>0</depth>
                        <hotspotX>0.5</hotspotX>
                        <hotspotY>0.5</hotspotY>
                        <angle>0</angle>
                        <opacity>1</opacity>
                    </world>
                </instance>
                <instance type="txtvei1" uid="918">
                    <properties>
                        <text>Item Errado!</text>
                        <initial-visibility>Invisible</initial-visibility>
                        <font>Tw Cen MT,-24,400,0</font>
                        <color>0,0,0</color>
                        <horizontal-alignment>Center</horizontal-alignment>
                        <vertical-alignment>Center</vertical-alignment>
                        <hotspot>Top-left</hotspot>
                        <wrapping>Word</wrapping>
                        <line-height>0</line-height>
                    </properties>
                    <blend-mode>0</blend-mode>
                    <effect-fallback>0</effect-fallback>
                    <world>
                        <x>173.39654541</x>
                        <y>123.020736694</y>
                        <z>0</z>
                        <width>103</width>
                        <height>59</height>
                        <depth>0</depth>
                        <hotspotX>0</hotspotX>
                        <hotspotY>0</hotspotY>
                        <angle>0</angle>
                        <opacity>1</opacity>
                    </world>
                </instance>
                <instance type="txtvei2" uid="919">
                    <properties>
                        <text>Nenhum Item!</text>
                        <initial-visibility>Invisible</initial-visibility>
                        <font>Tw Cen MT,-24,400,0</font>
                        <color>0,0,0</color>
                        <horizontal-alignment>Center</horizontal-alignment>
                        <vertical-alignment>Center</vertical-alignment>
                        <hotspot>Top-left</hotspot>
                        <wrapping>Word</wrapping>
                        <line-height>0</line-height>
                    </properties>
                    <blend-mode>0</blend-mode>
                    <effect-fallback>0</effect-fallback>
                    <world>
                        <x>175.085281372</x>
                        <y>121.581741333</y>
                        <z>0</z>
                        <width>112</width>
                        <height>57</height>
                        <depth>0</depth>
                        <hotspotX>0</hotspotX>
                        <hotspotY>0</hotspotY>
                        <angle>0</angle>
                        <opacity>1</opacity>
                    </world>
                </instance>
                <instance type="txtvei4" uid="923">
                    <properties>
                        <text>Pontos</text>
                        <initial-visibility>Visible</initial-visibility>
                        <font>Tw Cen MT,-27,400,0</font>
                        <color>0,0,0</color>
                        <horizontal-alignment>Left</horizontal-alignment>
                        <vertical-alignment>Top</vertical-alignment>
                        <hotspot>Top-left</hotspot>
                        <wrapping>Word</wrapping>
                        <line-height>0</line-height>
                    </properties>
                    <behavior-instances>
                        <behavior-instance type="Anchor">
                            <properties>
                                <left-edge>Window left</left-edge>
                                <top-edge>Window top</top-edge>
                                <right-edge>None</right-edge>
                                <bottom-edge>None</bottom-edge>
                                <initial-state>Enabled</initial-state>
                            </properties>
                        </behavior-instance>
                    </behavior-instances>
                    <blend-mode>0</blend-mode>
                    <effect-fallback>0</effect-fallback>
                    <world>
                        <x>38</x>
                        <y>47</y>
                        <z>0</z>
                        <width>215</width>
                        <height>50</height>
                        <depth>0</depth>
                        <hotspotX>0</hotspotX>
                        <hotspotY>0</hotspotY>
                        <angle>0</angle>
                        <opacity>1</opacity>
                    </world>
                </instance>
                <instance type="banc" uid="907">
                    <properties>
                        <initial-visibility>Visible</initial-visibility>
                        <initial-animation>Default</initial-animation>
                        <initial-frame>0</initial-frame>
                        <collisions>Enabled</collisions>
                    </properties>
                    <blend-mode>0</blend-mode>
                    <effect-fallback>0</effect-fallback>
                    <world>
                        <x>285.552001953</x>
                        <y>300.745666504</y>
                        <z>0</z>
                        <width>-196.460205078</width>
                        <height>-150.819519043</height>
                        <depth>0</depth>
                        <hotspotX>0.446366787</hotspotX>
                        <hotspotY>-0.126168221</hotspotY>
                        <angle>3.141592741</angle>
                        <opacity>1</opacity>
                    </world>
                </instance>
                <instance type="Sprite57" uid="906">
                    <properties>
                        <initial-visibility>Visible</initial-visibility>
                        <initial-animation>default</initial-animation>
                        <initial-frame>0</initial-frame>
                        <collisions>Enabled</collisions>
                    </properties>
                    <behavior-instances>
                        <behavior-instance type="Pin" />
                    </behavior-instances>
                    <blend-mode>0</blend-mode>
                    <effect-fallback>0</effect-fallback>
                    <world>
                        <x>457</x>
                        <y>470</y>
                        <z>0</z>
                        <width>-225</width>
                        <height>254</height>
                        <depth>0</depth>
                        <hotspotX>0.507246375</hotspotX>
                        <hotspotY>1</hotspotY>
                        <angle>0</angle>
                        <opacity>1</opacity>
                    </world>
                </instance>
                <instance type="imgLivroVendas2" uid="920">
                    <properties>
                        <initial-visibility>Invisible</initial-visibility>
                        <initial-animation>Default</initial-animation>
                        <initial-frame>0</initial-frame>
                        <collisions>Enabled</collisions>
                    </properties>
                    <behavior-instances>
                        <behavior-instance type="Pin" />
                    </behavior-instances>
                    <blend-mode>0</blend-mode>
                    <effect-fallback>0</effect-fallback>
                    <world>
                        <x>418</x>
                        <y>640</y>
                        <z>0</z>
                        <width>76</width>
                        <height>73</height>
                        <depth>0</depth>
                        <hotspotX>0.5</hotspotX>
                        <hotspotY>0.5</hotspotY>
                        <angle>0</angle>
                        <opacity>1</opacity>
                    </world>
                </instance>
                <instance type="mrnuuu" uid="921">
                    <properties>
                        <initial-visibility>Visible</initial-visibility>
                        <initial-animation>Default</initial-animation>
                        <initial-frame>0</initial-frame>
                        <collisions>Enabled</collisions>
                    </properties>
                    <blend-mode>0</blend-mode>
                    <effect-fallback>0</effect-fallback>
                    <world>
                        <x>801</x>
                        <y>761</y>
                        <z>0</z>
                        <width>502</width>
                        <height>384</height>
                        <depth>0</depth>
                        <hotspotX>0.505976081</hotspotX>
                        <hotspotY>0.484375</hotspotY>
                        <angle>0</angle>
                        <opacity>1</opacity>
                    </world>
                </instance>
                <instance type="txtvei3" uid="922">
                    <properties>
                        <text>VOCÊ GANHOU!</text>
                        <initial-visibility>Visible</initial-visibility>
                        <font>Elephant,-40,400,0</font>
                        <color>0,0,0</color>
                        <horizontal-alignment>Center</horizontal-alignment>
                        <vertical-alignment>Center</vertical-alignment>
                        <hotspot>Top-left</hotspot>
                        <wrapping>Word</wrapping>
                        <line-height>0</line-height>
                    </properties>
                    <blend-mode>0</blend-mode>
                    <effect-fallback>0</effect-fallback>
                    <world>
                        <x>570</x>
                        <y>631</y>
                        <z>0</z>
                        <width>448</width>
                        <height>64</height>
                        <depth>0</depth>
                        <hotspotX>0</hotspotX>
                        <hotspotY>0</hotspotY>
                        <angle>0</angle>
                        <opacity>1</opacity>
                    </world>
                </instance>
                <instance type="btnvei2" uid="924">
                    <properties>
                        <type>Button</type>
                        <text>MENU</text>
                        <tooltip></tooltip>
                        <initial-visibility>Visible</initial-visibility>
                        <enabled>Yes</enabled>
                        <auto-font-size>Yes</auto-font-size>
                        <id-optional></id-optional>
                        <checked>No</checked>
                    </properties>
                    <blend-mode>0</blend-mode>
                    <effect-fallback>0</effect-fallback>
                    <world>
                        <x>615</x>
                        <y>808</y>
                        <z>0</z>
                        <width>160</width>
                        <height>64</height>
                        <depth>0</depth>
                        <hotspotX>0</hotspotX>
                        <hotspotY>0</hotspotY>
                    </world>
                </instance>
                <instance type="txtvei5" uid="925">
                    <properties>
                        <text>Text</text>
                        <initial-visibility>Visible</initial-visibility>
                        <font>Arial,-16</font>
                        <color>0,0,0</color>
                        <horizontal-alignment>Left</horizontal-alignment>
                        <vertical-alignment>Top</vertical-alignment>
                        <hotspot>Top-left</hotspot>
                        <wrapping>Word</wrapping>
                        <line-height>0</line-height>
                    </properties>
                    <blend-mode>0</blend-mode>
                    <effect-fallback>0</effect-fallback>
                    <world>
                        <x>615</x>
                        <y>712</y>
                        <z>0</z>
                        <width>200</width>
                        <height>30</height>
                        <depth>0</depth>
                        <hotspotX>0</hotspotX>
                        <hotspotY>0</hotspotY>
                        <angle>0</angle>
                        <opacity>1</opacity>
                    </world>
                </instance>
                <instance type="btnvei" uid="926">
                    <properties>
                        <type>Button</type>
                        <text>JOGAR DE NOVO</text>
                        <tooltip></tooltip>
                        <initial-visibility>Visible</initial-visibility>
                        <enabled>Yes</enabled>
                        <auto-font-size>Yes</auto-font-size>
                        <id-optional></id-optional>
                        <checked>No</checked>
                    </properties>
                    <blend-mode>0</blend-mode>
                    <effect-fallback>0</effect-fallback>
                    <world>
                        <x>807</x>
                        <y>808</y>
                        <z>0</z>
                        <width>160</width>
                        <height>64</height>
                        <depth>0</depth>
                        <hotspotX>0</hotspotX>
                        <hotspotY>0</hotspotY>
                    </world>
                </instance>
            </instances>
            <effects />
        </layer>
    </layers>
    <nonworld-instances />
    <effects />
</c2layout>
